PythonDictExp/DictToList.py
PythonDictExp/MergeDict.py
PythonDictExp/__init__.py
Rits-0.0.7.dist-info/LICENSE
Rits-0.0.7.dist-info/METADATA
Rits-0.0.7.dist-info/WHEEL
Rits-0.0.7.dist-info/top_level.txt
Rits-0.0.7.dist-info/RECORD
