Metadata-Version: 2.1
Name: Rits
Version: 0.0.7
Summary: Rits
Home-page: UNKNOWN
Author: Ritika
Author-email: ritika.kumar90@gmail.com
License: UNKNOWN
Keywords: arithmetic,math,mathematics,python tutorial,Ritika kumar
Platform: UNKNOWN
Classifier: Development Status :: 1 - Planning
Classifier: Intended Audience :: Developers
Classifier: Programming Language :: Python :: 3
Classifier: Operating System :: Unix
Classifier: Operating System :: MacOS :: MacOS X
Classifier: Operating System :: Microsoft :: Windows
License-File: LICENSE
